commonvoice_pinyin/__init__.py
commonvoice_pinyin/common_voice.py
commonvoice_pinyin/common_voice_cached.py
commonvoice_pinyin/pinyin.py
commonvoice_pinyin/stats.py
commonvoice_pinyin-1.1.3.dist-info/LICENSE
commonvoice_pinyin-1.1.3.dist-info/METADATA
commonvoice_pinyin-1.1.3.dist-info/WHEEL
commonvoice_pinyin-1.1.3.dist-info/top_level.txt
commonvoice_pinyin-1.1.3.dist-info/RECORD
